terracheck/__init__.py
terracheck/checker/StructureChecker.py
terracheck/checker/StyleChecker.py
terracheck/checker/__init__.py
terracheck/io/HclCheckerReader.py
terracheck/io/__init__.py
terracheck/types/CheckerElement.py
terracheck/types/CheckerIssue.py
terracheck/types/RuleCategory.py
terracheck/types/TerraformBasicFileName.py
terracheck/types/TerraformObjectType.py
terracheck/types/__init__.py
terracheck/utils/__init__.py
terracheck/utils/utils.py
terracheck-0.2.0.dist-info/METADATA
terracheck-0.2.0.dist-info/WHEEL
terracheck-0.2.0.dist-info/top_level.txt
terracheck-0.2.0.dist-info/RECORD
