Metadata-Version: 2.1
Name: terracheck
Version: 0.2.0
Summary: Python Terraform checker from GCP good practices
Author: William Attache
Author-email: william.attache@mydevacademy.com
License: MIT
Keywords: terraform gcp goodpractices
Classifier: Development Status :: 3 - Alpha
Classifier: Intended Audience :: Developers
Classifier: Topic :: Utilities
Classifier: License :: OSI Approved :: MIT License
Classifier: Programming Language :: Python
Classifier: Programming Language :: Python :: 3
Classifier: Programming Language :: Python :: 3.8
Requires-Dist: python-hcl2 (==3.0.5)
Requires-Dist: colorama (==0.4.5)
Requires-Dist: pytest (==7.2.0)
Requires-Dist: PyYAML (==6.0)
